[{"currencyName":"AFN","countryName":"Afghan Afghani","amount":70.500003},{"currencyName":"ALL","countryName":"Albanian Lek","amount":83.799962},{"currencyName":"DZD","countryName":"Algerian Dinar","amount":129.633465},{"currencyName":"AOA","countryName":"Angolan Kwanza","amount":911.955},{"currencyName":"ARS","countryName":"Argentine Peso","amount":1193.9493},{"currencyName":"AMD","countryName":"Armenian Dram","amount":383.987091},{"currencyName":"AWG","countryName":"Aruban Florin","amount":1.8025},{"currencyName":"AUD","countryName":"Australian Dollar","amount":1.521562},{"currencyName":"AZN","countryName":"Azerbaijani Manat","amount":1.7},{"currencyName":"BSD","countryName":"Bahamian Dollar","amount":1},{"currencyName":"BHD","countryName":"Bahraini Dinar","amount":0.3773},{"currencyName":"BDT","countryName":"Bangladeshi Taka","amount":122.263354},{"currencyName":"BBD","countryName":"Barbadian Dollar","amount":2},{"currencyName":"BYN","countryName":"Belarusian Ruble","amount":3.272676},{"currencyName":"BZD","countryName":"Belize Dollar","amount":2.008725},{"currencyName":"BMD","countryName":"Bermudan Dollar","amount":1},{"currencyName":"BTN","countryName":"Bhutanese Ngultrum","amount":85.816283},{"currencyName":"BTC","countryName":"Bitcoin","amount":0.000009289668},{"currencyName":"BOB","countryName":"Bolivian Boliviano","amount":6.924904},{"currencyName":"BAM","countryName":"Bosnia-Herzegovina Convertible Mark","amount":1.669035},{"currencyName":"BWP","countryName":"Botswanan Pula","amount":13.307348},{"currencyName":"BRL","countryName":"Brazilian Real","amount":5.438896},{"currencyName":"GBP","countryName":"British Pound Sterling","amount":0.729132},{"currencyName":"BND","countryName":"Brunei Dollar","amount":1.274783},{"currencyName":"BGN","countryName":"Bulgarian Lev","amount":1.6664},{"currencyName":"BIF","countryName":"Burundian Franc","amount":2940},{"currencyName":"XOF","countryName":"CFA Franc BCEAO","amount":557.645781},{"currencyName":"XAF","countryName":"CFA Franc BEAC","amount":557.645781},{"currencyName":"XPF","countryName":"CFP Franc","amount":101.446959},{"currencyName":"KHR","countryName":"Cambodian Riel","amount":4020},{"currencyName":"CAD","countryName":"Canadian Dollar","amount":1.36264},{"currencyName":"CVE","countryName":"Cape Verdean Escudo","amount":94.625},{"currencyName":"KYD","countryName":"Cayman Islands Dollar","amount":0.833394},{"currencyName":"CLP","countryName":"Chilean Peso","amount":931.64},{"currencyName":"CLF","countryName":"Chilean Unit of Account (UF)","amount":0.024278},{"currencyName":"CNY","countryName":"Chinese Yuan","amount":7.1639},{"currencyName":"CNH","countryName":"Chinese Yuan (Offshore)","amount":7.15849},{"currencyName":"COP","countryName":"Colombian Peso","amount":4088.499303},{"currencyName":"KMF","countryName":"Comorian Franc","amount":420.499968},{"currencyName":"CDF","countryName":"Congolese Franc","amount":2881},{"currencyName":"CRC","countryName":"Costa Rican Colón","amount":504.675986},{"currencyName":"HRK","countryName":"Croatian Kuna","amount":6.407138},{"currencyName":"CUC","countryName":"Cuban Convertible Peso","amount":1},{"currencyName":"CUP","countryName":"Cuban Peso","amount":25.75},{"currencyName":"CZK","countryName":"Czech Republic Koruna","amount":21.021},{"currencyName":"DKK","countryName":"Danish Krone","amount":6.3426},{"currencyName":"DJF","countryName":"Djiboutian Franc","amount":178.082344},{"currencyName":"DOP","countryName":"Dominican Peso","amount":59.55},{"currencyName":"XCD","countryName":"East Caribbean Dollar","amount":2.70255},{"currencyName":"EGP","countryName":"Egyptian Pound","amount":49.5968},{"currencyName":"ERN","countryName":"Eritrean Nakfa","amount":15},{"currencyName":"ETB","countryName":"Ethiopian Birr","amount":137.183297},{"currencyName":"EUR","countryName":"Euro","amount":0.850126},{"currencyName":"FKP","countryName":"Falkland Islands Pound","amount":0.729132},{"currencyName":"FJD","countryName":"Fijian Dollar","amount":2.2347},{"currencyName":"GMD","countryName":"Gambian Dalasi","amount":71.500009},{"currencyName":"GEL","countryName":"Georgian Lari","amount":2.72},{"currencyName":"GHS","countryName":"Ghanaian Cedi","amount":10.325},{"currencyName":"GIP","countryName":"Gibraltar Pound","amount":0.729132},{"currencyName":"XAU","countryName":"Gold Ounce","amount":0.00030334},{"currencyName":"GTQ","countryName":"Guatemalan Quetzal","amount":7.688073},{"currencyName":"GGP","countryName":"Guernsey Pound","amount":0.729132},{"currencyName":"GNF","countryName":"Guinean Franc","amount":8655},{"currencyName":"GYD","countryName":"Guyanaese Dollar","amount":209.222746},{"currencyName":"HTG","countryName":"Haitian Gourde","amount":131.10318},{"currencyName":"HNL","countryName":"Honduran Lempira","amount":26.120164},{"currencyName":"HKD","countryName":"Hong Kong Dollar","amount":7.849965},{"currencyName":"HUF","countryName":"Hungarian Forint","amount":339.765648},{"currencyName":"ISK","countryName":"Icelandic Króna","amount":120.89},{"currencyName":"INR","countryName":"Indian Rupee","amount":85.695},{"currencyName":"IDR","countryName":"Indonesian Rupiah","amount":16152.4},{"currencyName":"IRR","countryName":"Iranian Rial","amount":42125},{"currencyName":"IQD","countryName":"Iraqi Dinar","amount":1310},{"currencyName":"ILS","countryName":"Israeli New Sheqel","amount":3.367613},{"currencyName":"JMD","countryName":"Jamaican Dollar","amount":160.204495},{"currencyName":"JPY","countryName":"Japanese Yen","amount":144.231},{"currencyName":"JEP","countryName":"Jersey Pound","amount":0.729132},{"currencyName":"JOD","countryName":"Jordanian Dinar","amount":0.709},{"currencyName":"KZT","countryName":"Kazakhstani Tenge","amount":520.224552},{"currencyName":"KES","countryName":"Kenyan Shilling","amount":129.5},{"currencyName":"KWD","countryName":"Kuwaiti Dinar","amount":0.305697},{"currencyName":"KGS","countryName":"Kyrgystani Som","amount":87.4292},{"currencyName":"LAK","countryName":"Laotian Kip","amount":21570},{"currencyName":"LBP","countryName":"Lebanese Pound","amount":89600},{"currencyName":"LSL","countryName":"Lesotho Loti","amount":17.87},{"currencyName":"LRD","countryName":"Liberian Dollar","amount":200.499906},{"currencyName":"LYD","countryName":"Libyan Dinar","amount":5.425},{"currencyName":"MOP","countryName":"Macanese Pataca","amount":8.086418},{"currencyName":"MKD","countryName":"Macedonian Denar","amount":52.282276},{"currencyName":"MGA","countryName":"Malagasy Ariary","amount":4392.555381},{"currencyName":"MWK","countryName":"Malawian Kwacha","amount":1736.5},{"currencyName":"MYR","countryName":"Malaysian Ringgit","amount":4.2285},{"currencyName":"MVR","countryName":"Maldivian Rufiyaa","amount":15.4},{"currencyName":"IMP","countryName":"Manx pound","amount":0.729132},{"currencyName":"MRU","countryName":"Mauritanian Ouguiya","amount":39.75},{"currencyName":"MUR","countryName":"Mauritian Rupee","amount":45.070002},{"currencyName":"MXN","countryName":"Mexican Peso","amount":18.814599},{"currencyName":"MDL","countryName":"Moldovan Leu","amount":16.819543},{"currencyName":"MNT","countryName":"Mongolian Tugrik","amount":3398},{"currencyName":"MAD","countryName":"Moroccan Dirham","amount":9.04625},{"currencyName":"MZN","countryName":"Mozambican Metical","amount":63.959999},{"currencyName":"MMK","countryName":"Myanma Kyat","amount":2098},{"currencyName":"NAD","countryName":"Namibian Dollar","amount":17.87},{"currencyName":"NPR","countryName":"Nepalese Rupee","amount":137.305708},{"currencyName":"ANG","countryName":"Netherlands Antillean Guilder","amount":1.79},{"currencyName":"TWD","countryName":"New Taiwan Dollar","amount":29.1939},{"currencyName":"NZD","countryName":"New Zealand Dollar","amount":1.642078},{"currencyName":"NIO","countryName":"Nicaraguan Córdoba","amount":36.789082},{"currencyName":"NGN","countryName":"Nigerian Naira","amount":1538.33},{"currencyName":"KPW","countryName":"North Korean Won","amount":900},{"currencyName":"NOK","countryName":"Norwegian Krone","amount":10.095067},{"currencyName":"OMR","countryName":"Omani Rial","amount":0.384515},{"currencyName":"PKR","countryName":"Pakistani Rupee","amount":285.053002},{"currencyName":"XPD","countryName":"Palladium Ounce","amount":0.00090945},{"currencyName":"PAB","countryName":"Panamanian Balboa","amount":1},{"currencyName":"PGK","countryName":"Papua New Guinean Kina","amount":4.123518},{"currencyName":"PYG","countryName":"Paraguayan Guarani","amount":7977.329267},{"currencyName":"PEN","countryName":"Peruvian Nuevo Sol","amount":3.548171},{"currencyName":"PHP","countryName":"Philippine Peso","amount":56.316496},{"currencyName":"XPT","countryName":"Platinum Ounce","amount":0.00075152},{"currencyName":"PLN","countryName":"Polish Zloty","amount":3.6101},{"currencyName":"QAR","countryName":"Qatari Rial","amount":3.6406},{"currencyName":"RON","countryName":"Romanian Leu","amount":4.3168},{"currencyName":"RUB","countryName":"Russian Ruble","amount":78.198342},{"currencyName":"RWF","countryName":"Rwandan Franc","amount":1432},{"currencyName":"SHP","countryName":"Saint Helena Pound","amount":0.729132},{"currencyName":"SVC","countryName":"Salvadoran Colón","amount":8.747114},{"currencyName":"WST","countryName":"Samoan Tala","amount":2.8},{"currencyName":"SAR","countryName":"Saudi Riyal","amount":3.750569},{"currencyName":"RSD","countryName":"Serbian Dinar","amount":99.613122},{"currencyName":"SCR","countryName":"Seychellois Rupee","amount":14.124436},{"currencyName":"SLL","countryName":"Sierra Leonean Leone","amount":20969.5},{"currencyName":"XAG","countryName":"Silver Ounce","amount":0.02777315},{"currencyName":"SGD","countryName":"Singapore Dollar","amount":1.272365},{"currencyName":"SBD","countryName":"Solomon Islands Dollar","amount":8.347338},{"currencyName":"SOS","countryName":"Somali Shilling","amount":571.5},{"currencyName":"ZAR","countryName":"South African Rand","amount":17.721849},{"currencyName":"KRW","countryName":"South Korean Won","amount":1353.553094},{"currencyName":"SSP","countryName":"South Sudanese Pound","amount":130.26},{"currencyName":"XDR","countryName":"Special Drawing Rights","amount":0.696185},{"currencyName":"LKR","countryName":"Sri Lankan Rupee","amount":299.829002},{"currencyName":"SDG","countryName":"Sudanese Pound","amount":600.5},{"currencyName":"SRD","countryName":"Surinamese Dollar","amount":37.2595},{"currencyName":"SZL","countryName":"Swazi Lilangeni","amount":17.87},{"currencyName":"SEK","countryName":"Swedish Krona","amount":9.47882},{"currencyName":"CHF","countryName":"Swiss Franc","amount":0.794203},{"currencyName":"SYP","countryName":"Syrian Pound","amount":13002},{"currencyName":"STN","countryName":"São Tomé and Príncipe Dobra","amount":21.3},{"currencyName":"STD","countryName":"São Tomé and Príncipe Dobra (pre-2018)","amount":22281.8},{"currencyName":"TJS","countryName":"Tajikistani Somoni","amount":9.90025},{"currencyName":"TZS","countryName":"Tanzanian Shilling","amount":2632.102},{"currencyName":"THB","countryName":"Thai Baht","amount":32.473743},{"currencyName":"TOP","countryName":"Tongan Pa'anga","amount":2.40776},{"currencyName":"TTD","countryName":"Trinidad and Tobago Dollar","amount":6.790995},{"currencyName":"TND","countryName":"Tunisian Dinar","amount":2.8795},{"currencyName":"TRY","countryName":"Turkish Lira","amount":39.825899},{"currencyName":"TMT","countryName":"Turkmenistani Manat","amount":3.51},{"currencyName":"UGX","countryName":"Ugandan Shilling","amount":3593.580717},{"currencyName":"UAH","countryName":"Ukrainian Hryvnia","amount":41.786468},{"currencyName":"AED","countryName":"United Arab Emirates Dirham","amount":3.67255},{"currencyName":"USD","countryName":"United States Dollar","amount":1},{"currencyName":"UYU","countryName":"Uruguayan Peso","amount":40.199167},{"currencyName":"UZS","countryName":"Uzbekistan Som","amount":12582.022191},{"currencyName":"VUV","countryName":"Vanuatu Vatu","amount":118.722},{"currencyName":"VES","countryName":"Venezuelan Bolívar Soberano","amount":106.603472},{"currencyName":"VND","countryName":"Vietnamese Dong","amount":26120.5},{"currencyName":"YER","countryName":"Yemeni Rial","amount":242.25004},{"currencyName":"ZMW","countryName":"Zambian Kwacha","amount":23.875951},{"currencyName":"ZWL","countryName":"Zimbabwean Dollar","amount":322}]